odoo10_addon_partner_academic_title-10.0.1.0.0-py2.7-nspkg.pth
odoo/addons/partner_academic_title/README.rst
odoo/addons/partner_academic_title/__init__.py
odoo/addons/partner_academic_title/__manifest__.py
odoo/addons/partner_academic_title/data/partner_academic_title_data.xml
odoo/addons/partner_academic_title/i18n/de.po
odoo/addons/partner_academic_title/i18n/es.po
odoo/addons/partner_academic_title/i18n/fi.po
odoo/addons/partner_academic_title/i18n/it.po
odoo/addons/partner_academic_title/i18n/sl.po
odoo/addons/partner_academic_title/models/__init__.py
odoo/addons/partner_academic_title/models/partner_academic_title.py
odoo/addons/partner_academic_title/models/res_partner.py
odoo/addons/partner_academic_title/security/ir.model.access.csv
odoo/addons/partner_academic_title/views/partner_academic_title_view.xml
odoo/addons/partner_academic_title/views/res_partner_view.xml
odoo10_addon_partner_academic_title-10.0.1.0.0.dist-info/DESCRIPTION.rst
odoo10_addon_partner_academic_title-10.0.1.0.0.dist-info/METADATA
odoo10_addon_partner_academic_title-10.0.1.0.0.dist-info/RECORD
odoo10_addon_partner_academic_title-10.0.1.0.0.dist-info/WHEEL
odoo10_addon_partner_academic_title-10.0.1.0.0.dist-info/metadata.json
odoo10_addon_partner_academic_title-10.0.1.0.0.dist-info/namespace_packages.txt
odoo10_addon_partner_academic_title-10.0.1.0.0.dist-info/top_level.txt
